pyRubiCo/Clien.py
pyRubiCo/Copyright.py
pyRubiCo/Device.py
pyRubiCo/Encoder.py
pyRubiCo/Error.py
pyRubiCo/Getheader.py
pyRubiCo/GtM.py
pyRubiCo/PostData.py
pyRubiCo/TypeText.py
pyRubiCo/Zedcontent.py
pyRubiCo/__init__.py
pyRubiCo/pyRubiCo.py
pyRubiCo/setup.py
pyRubiCo-2023.3.1.dist-info/LICENCE
pyRubiCo-2023.3.1.dist-info/METADATA
pyRubiCo-2023.3.1.dist-info/WHEEL
pyRubiCo-2023.3.1.dist-info/top_level.txt
pyRubiCo-2023.3.1.dist-info/RECORD
