Metadata-Version: 2.1
Name: pyRubiCo
Version: 2023.3.1
Summary: library Robot Rubika
Author-email: Ali Eslami <pyrubico@gmail.com>
Project-URL: Homepage, https://github.com/alitektanus/RubiCo.git
Project-URL: Bug Tracker, https://github.com/alitektanus/RubiCo.git
Classifier: Programming Language :: Python :: 3
Classifier: License :: OSI Approved :: MIT License
Classifier: Operating System :: OS Independent
Requires-Python: >=3.11
License-File: LICENCE
